.DS_Store
psg_utils/.DS_Store
psg_utils/__init__.py
psg_utils/_defaults.py
psg_utils/time_utils.py
psg_utils/utils.py
psg_utils/version.py
psg_utils/dataset/.DS_Store
psg_utils/dataset/__init__.py
psg_utils/dataset/utils.py
psg_utils/dataset/queue/__init__.py
psg_utils/dataset/queue/base_queue.py
psg_utils/dataset/queue/eager_queue.py
psg_utils/dataset/queue/lazy_queue.py
psg_utils/dataset/queue/limitation_queue.py
psg_utils/dataset/queue/study_loader.py
psg_utils/dataset/queue/utils.py
psg_utils/dataset/sleep_study/__init__.py
psg_utils/dataset/sleep_study/abc_sleep_study.py
psg_utils/dataset/sleep_study/h5_sleep_study.py
psg_utils/dataset/sleep_study/sleep_study.py
psg_utils/dataset/sleep_study/subject_dir_sleep_study_base.py
psg_utils/dataset/sleep_study_dataset/__init__.py
psg_utils/dataset/sleep_study_dataset/abc_sleep_study_dataset.py
psg_utils/dataset/sleep_study_dataset/single_h5_dataset.py
psg_utils/dataset/sleep_study_dataset/sleep_study_dataset.py
psg_utils/dataset/sleep_study_dataset/subject_dir_sleep_study_dataset_base.py
psg_utils/downloads/.DS_Store
psg_utils/downloads/__init__.py
psg_utils/downloads/utils.py
psg_utils/downloads/dcsm/__init__.py
psg_utils/downloads/dcsm/dcsm.py
psg_utils/downloads/dcsm/dcsm_checksums.txt
psg_utils/downloads/phys/__init__.py
psg_utils/downloads/phys/phys.py
psg_utils/downloads/phys/phys_checksums.txt
psg_utils/downloads/sedf/__init__.py
psg_utils/downloads/sedf/sedf.py
psg_utils/downloads/sedf/sedf_sc_checksums.txt
psg_utils/downloads/sedf/sedf_st_checksums.txt
psg_utils/errors/__init__.py
psg_utils/hypnogram/__init__.py
psg_utils/hypnogram/formats.py
psg_utils/hypnogram/hypnograms.py
psg_utils/hypnogram/stage_mapper.py
psg_utils/hypnogram/utils.py
psg_utils/io/.DS_Store
psg_utils/io/__init__.py
psg_utils/io/file_writers.py
psg_utils/io/high_level_file_loaders.py
psg_utils/io/channels/__init__.py
psg_utils/io/channels/channel_types.py
psg_utils/io/channels/channels.py
psg_utils/io/channels/montage_creator.py
psg_utils-0.1.6.dist-info/LICENSE
psg_utils-0.1.6.dist-info/METADATA
psg_utils-0.1.6.dist-info/WHEEL
psg_utils-0.1.6.dist-info/top_level.txt
psg_utils-0.1.6.dist-info/RECORD
